ya_pickledb/__init__.py
ya_pickledb/cache.py
ya_pickledb/errors.py
ya_pickledb/pickledb.py
ya_pickledb-0.2.0.dist-info/LICENSE
ya_pickledb-0.2.0.dist-info/METADATA
ya_pickledb-0.2.0.dist-info/WHEEL
ya_pickledb-0.2.0.dist-info/RECORD
