Metadata-Version: 2.1
Name: ya_pickledb
Version: 0.2.0
Summary: Yet another PickleDB (thread-safe!)
License: MIT
Author: Angelo Delicato
Author-email: thelicato@duck.com
Requires-Python: >=3.9,<4.0
Classifier: License :: OSI Approved :: MIT License
Classifier: Programming Language :: Python :: 3
Classifier: Programming Language :: Python :: 3.9
Classifier: Programming Language :: Python :: 3.10
Classifier: Programming Language :: Python :: 3.11
Classifier: Programming Language :: Python :: 3.12
Requires-Dist: msgpack (>=1.0.7,<2.0.0)
Requires-Dist: safer (>=4.12.3,<5.0.0)
